vintasend/__init__.py
vintasend/app_settings.py
vintasend/constants.py
vintasend/exceptions.py
vintasend/py.typed
vintasend/services/__init__.py
vintasend/services/dataclasses.py
vintasend/services/helpers.py
vintasend/services/notification_adapters/__init__.py
vintasend/services/notification_adapters/async_base.py
vintasend/services/notification_adapters/asyncio_base.py
vintasend/services/notification_adapters/base.py
vintasend/services/notification_adapters/stubs/__init__.py
vintasend/services/notification_adapters/stubs/fake_adapter.py
vintasend/services/notification_adapters/stubs/fake_in_app_adapter.py
vintasend/services/notification_backends/__init__.py
vintasend/services/notification_backends/asyncio_base.py
vintasend/services/notification_backends/base.py
vintasend/services/notification_backends/stubs/__init__.py
vintasend/services/notification_backends/stubs/fake_backend.py
vintasend/services/notification_service.py
vintasend/services/notification_template_renderers/__init__.py
vintasend/services/notification_template_renderers/base.py
vintasend/services/notification_template_renderers/base_templated_email_renderer.py
vintasend/services/notification_template_renderers/base_templated_sms_renderer.py
vintasend/services/notification_template_renderers/stubs/__init__.py
vintasend/services/notification_template_renderers/stubs/fake_templated_email_renderer.py
vintasend/services/utils.py
vintasend/tasks/__init__.py
vintasend/tasks/background_tasks.py
vintasend/tasks/periodic_tasks.py
vintasend/tests/__init__.py
vintasend/tests/test_services/__init__.py
vintasend/tests/test_services/test_notification_attachments.py
vintasend/tests/test_services/test_notification_service.py
vintasend/utils/__init__.py
vintasend/utils/singleton_utils.py
vintasend-1.0.1.dist-info/METADATA
vintasend-1.0.1.dist-info/WHEEL
vintasend-1.0.1.dist-info/licenses/LICENSE.txt
vintasend-1.0.1.dist-info/RECORD
