Metadata-Version: 2.4
Name: vintasend
Version: 1.0.1
Summary: A flexible package for implementing transactional notifications
License: MIT
License-File: LICENSE.txt
Author: Hugo bessa
Author-email: hugo@vinta.com.br
Requires-Python: >=3.9,<3.14
Classifier: License :: OSI Approved :: MIT License
Classifier: Programming Language :: Python :: 3
Classifier: Programming Language :: Python :: 3.9
Classifier: Programming Language :: Python :: 3.10
Classifier: Programming Language :: Python :: 3.11
Classifier: Programming Language :: Python :: 3.12
Classifier: Programming Language :: Python :: 3.13
Requires-Dist: packaging (>=25.0,<26.0)
Requires-Dist: pytest-asyncio (>=0.24.0,<0.25.0)
Requires-Dist: requests (>=2.32.5,<3.0.0)
Requires-Dist: typing-extensions (>=4.12.2,<5.0.0)
